astrometry_net_client/__init__.py
astrometry_net_client/client.py
astrometry_net_client/config.py
astrometry_net_client/exceptions.py
astrometry_net_client/request.py
astrometry_net_client/session.py
astrometry_net_client/settings.py
astrometry_net_client/statusables.py
astrometry_net_client/uploads.py
astrometry_net_client/scripts/anc_upload.py
astrometry_net_client-0.6.0.dist-info/licenses/LICENSE
astrometry_net_client-0.6.0.dist-info/METADATA
astrometry_net_client-0.6.0.dist-info/WHEEL
astrometry_net_client-0.6.0.dist-info/entry_points.txt
astrometry_net_client-0.6.0.dist-info/top_level.txt
astrometry_net_client-0.6.0.dist-info/RECORD
