Metadata-Version: 2.4
Name: astrometry_net_client
Version: 0.6.0
Summary: A Python interface for the Astrometry.net API.
Author-email: Sten Sipma <sten.sipma@ziggo.nl>
Project-URL: Repository, https://github.com/StenSipma/astrometry_net_client
Project-URL: Documentation, https://astrometry-net-client.readthedocs.io/en/latest/index.html
Keywords: astronomy,astrometry,client,coordinates,wcs,api
Classifier: Development Status :: 4 - Beta
Classifier: Intended Audience :: Science/Research
Classifier: License :: OSI Approved :: MIT License
Classifier: Programming Language :: Python :: 3.11
Classifier: Programming Language :: Python :: 3.12
Classifier: Programming Language :: Python :: 3.13
Classifier: Topic :: Scientific/Engineering :: Astronomy
Classifier: Topic :: Scientific/Engineering :: Image Recognition
Classifier: Operating System :: POSIX :: Linux
Classifier: Natural Language :: English
Requires-Python: >=3.11
License-File: LICENSE
Requires-Dist: astropy
Requires-Dist: requests
Dynamic: license-file
